{
  "project": "Project A",
  "step": "Step 16",
  "scope": "oracle-only benefit anatomy; not SOTA",
  "n_runs": 54,
  "n_beneficial": 5,
  "n_harmful": 43,
  "n_near_zero": 6,
  "benefit_rate": 0.0926,
  "benefit_estimand": "balanced_accuracy_gain (eps 0.005); policies use accuracy_gain",
  "n_beneficial_acc": 8,
  "benefit_rate_acc": 0.1481,
  "per_dataset": {
    "BNCI2014_001": {
      "n": 27,
      "n_beneficial": 3,
      "benefit_rate": 0.1111
    },
    "BNCI2014_004": {
      "n": 27,
      "n_beneficial": 2,
      "benefit_rate": 0.0741
    }
  },
  "per_target": {
    "BNCI2014_001:1": {
      "n_seeds": 3,
      "benefit_count": 0,
      "sign_consistent": true,
      "mean_gain_bacc": -0.118055
    },
    "BNCI2014_001:2": {
      "n_seeds": 3,
      "benefit_count": 0,
      "sign_consistent": true,
      "mean_gain_bacc": -0.038773
    },
    "BNCI2014_001:3": {
      "n_seeds": 3,
      "benefit_count": 0,
      "sign_consistent": true,
      "mean_gain_bacc": -0.07581
    },
    "BNCI2014_001:4": {
      "n_seeds": 3,
      "benefit_count": 0,
      "sign_consistent": true,
      "mean_gain_bacc": -0.050347
    },
    "BNCI2014_001:5": {
      "n_seeds": 3,
      "benefit_count": 1,
      "sign_consistent": false,
      "mean_gain_bacc": -0.0
    },
    "BNCI2014_001:6": {
      "n_seeds": 3,
      "benefit_count": 2,
      "sign_consistent": false,
      "mean_gain_bacc": 0.001736
    },
    "BNCI2014_001:7": {
      "n_seeds": 3,
      "benefit_count": 0,
      "sign_consistent": true,
      "mean_gain_bacc": -0.021412
    },
    "BNCI2014_001:8": {
      "n_seeds": 3,
      "benefit_count": 0,
      "sign_consistent": true,
      "mean_gain_bacc": -0.141782
    },
    "BNCI2014_001:9": {
      "n_seeds": 3,
      "benefit_count": 0,
      "sign_consistent": false,
      "mean_gain_bacc": -0.031829
    },
    "BNCI2014_004:1": {
      "n_seeds": 3,
      "benefit_count": 0,
      "sign_consistent": true,
      "mean_gain_bacc": -0.063889
    },
    "BNCI2014_004:2": {
      "n_seeds": 3,
      "benefit_count": 1,
      "sign_consistent": false,
      "mean_gain_bacc": -0.003431
    },
    "BNCI2014_004:3": {
      "n_seeds": 3,
      "benefit_count": 0,
      "sign_consistent": false,
      "mean_gain_bacc": -0.014815
    },
    "BNCI2014_004:4": {
      "n_seeds": 3,
      "benefit_count": 1,
      "sign_consistent": false,
      "mean_gain_bacc": 0.003153
    },
    "BNCI2014_004:5": {
      "n_seeds": 3,
      "benefit_count": 0,
      "sign_consistent": true,
      "mean_gain_bacc": -0.044144
    },
    "BNCI2014_004:6": {
      "n_seeds": 3,
      "benefit_count": 0,
      "sign_consistent": false,
      "mean_gain_bacc": -0.042593
    },
    "BNCI2014_004:7": {
      "n_seeds": 3,
      "benefit_count": 0,
      "sign_consistent": true,
      "mean_gain_bacc": -0.027778
    },
    "BNCI2014_004:8": {
      "n_seeds": 3,
      "benefit_count": 0,
      "sign_consistent": true,
      "mean_gain_bacc": -0.061403
    },
    "BNCI2014_004:9": {
      "n_seeds": 3,
      "benefit_count": 0,
      "sign_consistent": true,
      "mean_gain_bacc": -0.030093
    }
  },
  "per_seed": {
    "0": {
      "n": 18,
      "benefit_rate": 0.0556
    },
    "1": {
      "n": 18,
      "benefit_rate": 0.1111
    },
    "2": {
      "n": 18,
      "benefit_rate": 0.1111
    }
  },
  "target_sign_consistency_rate": 0.6111,
  "gain_distribution_bacc": {
    "mean": -0.042293,
    "std": 0.048183,
    "min": -0.208333,
    "max": 0.017361,
    "q10": -0.099696,
    "q50": -0.03559,
    "q90": 0.003879
  },
  "beneficial_gain_distribution_bacc": {
    "mean": 0.010553,
    "std": 0.004094,
    "min": 0.005882,
    "max": 0.017361,
    "q10": 0.006307,
    "q50": 0.010417,
    "q90": 0.015281
  },
  "runs": [
    {
      "dataset": "BNCI2014_001",
      "target_subject": 1,
      "seed": 0,
      "n_trials": 576,
      "identity_bacc": 0.529514,
      "adapt_bacc": 0.480903,
      "oracle_gain_bacc": -0.048611,
      "oracle_gain_acc": -0.048611,
      "beneficial": false,
      "harmful": true,
      "near_zero": false,
      "gain_abs": 0.048611,
      "gain_bin": "harm",
      "oracle_only": true
    },
    {
      "dataset": "BNCI2014_001",
      "target_subject": 1,
      "seed": 1,
      "n_trials": 576,
      "identity_bacc": 0.524306,
      "adapt_bacc": 0.319444,
      "oracle_gain_bacc": -0.204861,
      "oracle_gain_acc": -0.204861,
      "beneficial": false,
      "harmful": true,
      "near_zero": false,
      "gain_abs": 0.204861,
      "gain_bin": "harm",
      "oracle_only": true
    },
    {
      "dataset": "BNCI2014_001",
      "target_subject": 1,
      "seed": 2,
      "n_trials": 576,
      "identity_bacc": 0.532986,
      "adapt_bacc": 0.432292,
      "oracle_gain_bacc": -0.100694,
      "oracle_gain_acc": -0.100694,
      "beneficial": false,
      "harmful": true,
      "near_zero": false,
      "gain_abs": 0.100694,
      "gain_bin": "harm",
      "oracle_only": true
    },
    {
      "dataset": "BNCI2014_001",
      "target_subject": 2,
      "seed": 0,
      "n_trials": 576,
      "identity_bacc": 0.289931,
      "adapt_bacc": 0.25,
      "oracle_gain_bacc": -0.039931,
      "oracle_gain_acc": -0.039931,
      "beneficial": false,
      "harmful": true,
      "near_zero": false,
      "gain_abs": 0.039931,
      "gain_bin": "harm",
      "oracle_only": true
    },
    {
      "dataset": "BNCI2014_001",
      "target_subject": 2,
      "seed": 1,
      "n_trials": 576,
      "identity_bacc": 0.289931,
      "adapt_bacc": 0.25,
      "oracle_gain_bacc": -0.039931,
      "oracle_gain_acc": -0.039931,
      "beneficial": false,
      "harmful": true,
      "near_zero": false,
      "gain_abs": 0.039931,
      "gain_bin": "harm",
      "oracle_only": true
    },
    {
      "dataset": "BNCI2014_001",
      "target_subject": 2,
      "seed": 2,
      "n_trials": 576,
      "identity_bacc": 0.286458,
      "adapt_bacc": 0.25,
      "oracle_gain_bacc": -0.036458,
      "oracle_gain_acc": -0.036458,
      "beneficial": false,
      "harmful": true,
      "near_zero": false,
      "gain_abs": 0.036458,
      "gain_bin": "harm",
      "oracle_only": true
    },
    {
      "dataset": "BNCI2014_001",
      "target_subject": 3,
      "seed": 0,
      "n_trials": 576,
      "identity_bacc": 0.519097,
      "adapt_bacc": 0.40625,
      "oracle_gain_bacc": -0.112847,
      "oracle_gain_acc": -0.112847,
      "beneficial": false,
      "harmful": true,
      "near_zero": false,
      "gain_abs": 0.112847,
      "gain_bin": "harm",
      "oracle_only": true
    },
    {
      "dataset": "BNCI2014_001",
      "target_subject": 3,
      "seed": 1,
      "n_trials": 576,
      "identity_bacc": 0.498264,
      "adapt_bacc": 0.491319,
      "oracle_gain_bacc": -0.006944,
      "oracle_gain_acc": -0.006944,
      "beneficial": false,
      "harmful": true,
      "near_zero": false,
      "gain_abs": 0.006944,
      "gain_bin": "harm",
      "oracle_only": true
    },
    {
      "dataset": "BNCI2014_001",
      "target_subject": 3,
      "seed": 2,
      "n_trials": 576,
      "identity_bacc": 0.447917,
      "adapt_bacc": 0.340278,
      "oracle_gain_bacc": -0.107639,
      "oracle_gain_acc": -0.107639,
      "beneficial": false,
      "harmful": true,
      "near_zero": false,
      "gain_abs": 0.107639,
      "gain_bin": "harm",
      "oracle_only": true
    },
    {
      "dataset": "BNCI2014_001",
      "target_subject": 4,
      "seed": 0,
      "n_trials": 576,
      "identity_bacc": 0.347222,
      "adapt_bacc": 0.291667,
      "oracle_gain_bacc": -0.055556,
      "oracle_gain_acc": -0.055556,
      "beneficial": false,
      "harmful": true,
      "near_zero": false,
      "gain_abs": 0.055556,
      "gain_bin": "harm",
      "oracle_only": true
    },
    {
      "dataset": "BNCI2014_001",
      "target_subject": 4,
      "seed": 1,
      "n_trials": 576,
      "identity_bacc": 0.375,
      "adapt_bacc": 0.315972,
      "oracle_gain_bacc": -0.059028,
      "oracle_gain_acc": -0.059028,
      "beneficial": false,
      "harmful": true,
      "near_zero": false,
      "gain_abs": 0.059028,
      "gain_bin": "harm",
      "oracle_only": true
    },
    {
      "dataset": "BNCI2014_001",
      "target_subject": 4,
      "seed": 2,
      "n_trials": 576,
      "identity_bacc": 0.354167,
      "adapt_bacc": 0.317708,
      "oracle_gain_bacc": -0.036458,
      "oracle_gain_acc": -0.036458,
      "beneficial": false,
      "harmful": true,
      "near_zero": false,
      "gain_abs": 0.036458,
      "gain_bin": "harm",
      "oracle_only": true
    },
    {
      "dataset": "BNCI2014_001",
      "target_subject": 5,
      "seed": 0,
      "n_trials": 576,
      "identity_bacc": 0.255208,
      "adapt_bacc": 0.25,
      "oracle_gain_bacc": -0.005208,
      "oracle_gain_acc": -0.005208,
      "beneficial": false,
      "harmful": true,
      "near_zero": false,
      "gain_abs": 0.005208,
      "gain_bin": "harm",
      "oracle_only": true
    },
    {
      "dataset": "BNCI2014_001",
      "target_subject": 5,
      "seed": 1,
      "n_trials": 576,
      "identity_bacc": 0.267361,
      "adapt_bacc": 0.274306,
      "oracle_gain_bacc": 0.006944,
      "oracle_gain_acc": 0.006944,
      "beneficial": true,
      "harmful": false,
      "near_zero": false,
      "gain_abs": 0.006944,
      "gain_bin": "benefit",
      "oracle_only": true
    },
    {
      "dataset": "BNCI2014_001",
      "target_subject": 5,
      "seed": 2,
      "n_trials": 576,
      "identity_bacc": 0.251736,
      "adapt_bacc": 0.25,
      "oracle_gain_bacc": -0.001736,
      "oracle_gain_acc": -0.001736,
      "beneficial": false,
      "harmful": false,
      "near_zero": true,
      "gain_abs": 0.001736,
      "gain_bin": "near_zero",
      "oracle_only": true
    },
    {
      "dataset": "BNCI2014_001",
      "target_subject": 6,
      "seed": 0,
      "n_trials": 576,
      "identity_bacc": 0.347222,
      "adapt_bacc": 0.364583,
      "oracle_gain_bacc": 0.017361,
      "oracle_gain_acc": 0.017361,
      "beneficial": true,
      "harmful": false,
      "near_zero": false,
      "gain_abs": 0.017361,
      "gain_bin": "benefit",
      "oracle_only": true
    },
    {
      "dataset": "BNCI2014_001",
      "target_subject": 6,
      "seed": 1,
      "n_trials": 576,
      "identity_bacc": 0.371528,
      "adapt_bacc": 0.381944,
      "oracle_gain_bacc": 0.010417,
      "oracle_gain_acc": 0.010417,
      "beneficial": true,
      "harmful": false,
      "near_zero": false,
      "gain_abs": 0.010417,
      "gain_bin": "benefit",
      "oracle_only": true
    },
    {
      "dataset": "BNCI2014_001",
      "target_subject": 6,
      "seed": 2,
      "n_trials": 576,
      "identity_bacc": 0.328125,
      "adapt_bacc": 0.305556,
      "oracle_gain_bacc": -0.022569,
      "oracle_gain_acc": -0.022569,
      "beneficial": false,
      "harmful": true,
      "near_zero": false,
      "gain_abs": 0.022569,
      "gain_bin": "harm",
      "oracle_only": true
    },
    {
      "dataset": "BNCI2014_001",
      "target_subject": 7,
      "seed": 0,
      "n_trials": 576,
      "identity_bacc": 0.291667,
      "adapt_bacc": 0.267361,
      "oracle_gain_bacc": -0.024306,
      "oracle_gain_acc": -0.024306,
      "beneficial": false,
      "harmful": true,
      "near_zero": false,
      "gain_abs": 0.024306,
      "gain_bin": "harm",
      "oracle_only": true
    },
    {
      "dataset": "BNCI2014_001",
      "target_subject": 7,
      "seed": 1,
      "n_trials": 576,
      "identity_bacc": 0.286458,
      "adapt_bacc": 0.28125,
      "oracle_gain_bacc": -0.005208,
      "oracle_gain_acc": -0.005208,
      "beneficial": false,
      "harmful": true,
      "near_zero": false,
      "gain_abs": 0.005208,
      "gain_bin": "harm",
      "oracle_only": true
    },
    {
      "dataset": "BNCI2014_001",
      "target_subject": 7,
      "seed": 2,
      "n_trials": 576,
      "identity_bacc": 0.289931,
      "adapt_bacc": 0.255208,
      "oracle_gain_bacc": -0.034722,
      "oracle_gain_acc": -0.034722,
      "beneficial": false,
      "harmful": true,
      "near_zero": false,
      "gain_abs": 0.034722,
      "gain_bin": "harm",
      "oracle_only": true
    },
    {
      "dataset": "BNCI2014_001",
      "target_subject": 8,
      "seed": 0,
      "n_trials": 576,
      "identity_bacc": 0.560764,
      "adapt_bacc": 0.513889,
      "oracle_gain_bacc": -0.046875,
      "oracle_gain_acc": -0.046875,
      "beneficial": false,
      "harmful": true,
      "near_zero": false,
      "gain_abs": 0.046875,
      "gain_bin": "harm",
      "oracle_only": true
    },
    {
      "dataset": "BNCI2014_001",
      "target_subject": 8,
      "seed": 1,
      "n_trials": 576,
      "identity_bacc": 0.498264,
      "adapt_bacc": 0.289931,
      "oracle_gain_bacc": -0.208333,
      "oracle_gain_acc": -0.208333,
      "beneficial": false,
      "harmful": true,
      "near_zero": false,
      "gain_abs": 0.208333,
      "gain_bin": "harm",
      "oracle_only": true
    },
    {
      "dataset": "BNCI2014_001",
      "target_subject": 8,
      "seed": 2,
      "n_trials": 576,
      "identity_bacc": 0.480903,
      "adapt_bacc": 0.310764,
      "oracle_gain_bacc": -0.170139,
      "oracle_gain_acc": -0.170139,
      "beneficial": false,
      "harmful": true,
      "near_zero": false,
      "gain_abs": 0.170139,
      "gain_bin": "harm",
      "oracle_only": true
    },
    {
      "dataset": "BNCI2014_001",
      "target_subject": 9,
      "seed": 0,
      "n_trials": 576,
      "identity_bacc": 0.489583,
      "adapt_bacc": 0.446181,
      "oracle_gain_bacc": -0.043403,
      "oracle_gain_acc": -0.043403,
      "beneficial": false,
      "harmful": true,
      "near_zero": false,
      "gain_abs": 0.043403,
      "gain_bin": "harm",
      "oracle_only": true
    },
    {
      "dataset": "BNCI2014_001",
      "target_subject": 9,
      "seed": 1,
      "n_trials": 576,
      "identity_bacc": 0.428819,
      "adapt_bacc": 0.373264,
      "oracle_gain_bacc": -0.055556,
      "oracle_gain_acc": -0.055556,
      "beneficial": false,
      "harmful": true,
      "near_zero": false,
      "gain_abs": 0.055556,
      "gain_bin": "harm",
      "oracle_only": true
    },
    {
      "dataset": "BNCI2014_001",
      "target_subject": 9,
      "seed": 2,
      "n_trials": 576,
      "identity_bacc": 0.40625,
      "adapt_bacc": 0.409722,
      "oracle_gain_bacc": 0.003472,
      "oracle_gain_acc": 0.003472,
      "beneficial": false,
      "harmful": false,
      "near_zero": true,
      "gain_abs": 0.003472,
      "gain_bin": "near_zero",
      "oracle_only": true
    },
    {
      "dataset": "BNCI2014_004",
      "target_subject": 1,
      "seed": 0,
      "n_trials": 720,
      "identity_bacc": 0.655556,
      "adapt_bacc": 0.6125,
      "oracle_gain_bacc": -0.043056,
      "oracle_gain_acc": -0.043056,
      "beneficial": false,
      "harmful": true,
      "near_zero": false,
      "gain_abs": 0.043056,
      "gain_bin": "harm",
      "oracle_only": true
    },
    {
      "dataset": "BNCI2014_004",
      "target_subject": 1,
      "seed": 1,
      "n_trials": 720,
      "identity_bacc": 0.656944,
      "adapt_bacc": 0.601389,
      "oracle_gain_bacc": -0.055556,
      "oracle_gain_acc": -0.055556,
      "beneficial": false,
      "harmful": true,
      "near_zero": false,
      "gain_abs": 0.055556,
      "gain_bin": "harm",
      "oracle_only": true
    },
    {
      "dataset": "BNCI2014_004",
      "target_subject": 1,
      "seed": 2,
      "n_trials": 720,
      "identity_bacc": 0.668056,
      "adapt_bacc": 0.575,
      "oracle_gain_bacc": -0.093056,
      "oracle_gain_acc": -0.093056,
      "beneficial": false,
      "harmful": true,
      "near_zero": false,
      "gain_abs": 0.093056,
      "gain_bin": "harm",
      "oracle_only": true
    },
    {
      "dataset": "BNCI2014_004",
      "target_subject": 2,
      "seed": 0,
      "n_trials": 680,
      "identity_bacc": 0.519118,
      "adapt_bacc": 0.516176,
      "oracle_gain_bacc": -0.002941,
      "oracle_gain_acc": -0.002941,
      "beneficial": false,
      "harmful": false,
      "near_zero": true,
      "gain_abs": 0.002941,
      "gain_bin": "near_zero",
      "oracle_only": true
    },
    {
      "dataset": "BNCI2014_004",
      "target_subject": 2,
      "seed": 1,
      "n_trials": 680,
      "identity_bacc": 0.541176,
      "adapt_bacc": 0.527941,
      "oracle_gain_bacc": -0.013235,
      "oracle_gain_acc": -0.013235,
      "beneficial": false,
      "harmful": true,
      "near_zero": false,
      "gain_abs": 0.013235,
      "gain_bin": "harm",
      "oracle_only": true
    },
    {
      "dataset": "BNCI2014_004",
      "target_subject": 2,
      "seed": 2,
      "n_trials": 680,
      "identity_bacc": 0.522059,
      "adapt_bacc": 0.527941,
      "oracle_gain_bacc": 0.005882,
      "oracle_gain_acc": 0.005882,
      "beneficial": true,
      "harmful": false,
      "near_zero": false,
      "gain_abs": 0.005882,
      "gain_bin": "benefit",
      "oracle_only": true
    },
    {
      "dataset": "BNCI2014_004",
      "target_subject": 3,
      "seed": 0,
      "n_trials": 720,
      "identity_bacc": 0.543056,
      "adapt_bacc": 0.544444,
      "oracle_gain_bacc": 0.001389,
      "oracle_gain_acc": 0.001389,
      "beneficial": false,
      "harmful": false,
      "near_zero": true,
      "gain_abs": 0.001389,
      "gain_bin": "near_zero",
      "oracle_only": true
    },
    {
      "dataset": "BNCI2014_004",
      "target_subject": 3,
      "seed": 1,
      "n_trials": 720,
      "identity_bacc": 0.556944,
      "adapt_bacc": 0.534722,
      "oracle_gain_bacc": -0.022222,
      "oracle_gain_acc": -0.022222,
      "beneficial": false,
      "harmful": true,
      "near_zero": false,
      "gain_abs": 0.022222,
      "gain_bin": "harm",
      "oracle_only": true
    },
    {
      "dataset": "BNCI2014_004",
      "target_subject": 3,
      "seed": 2,
      "n_trials": 720,
      "identity_bacc": 0.552778,
      "adapt_bacc": 0.529167,
      "oracle_gain_bacc": -0.023611,
      "oracle_gain_acc": -0.023611,
      "beneficial": false,
      "harmful": true,
      "near_zero": false,
      "gain_abs": 0.023611,
      "gain_bin": "harm",
      "oracle_only": true
    },
    {
      "dataset": "BNCI2014_004",
      "target_subject": 4,
      "seed": 0,
      "n_trials": 740,
      "identity_bacc": 0.735135,
      "adapt_bacc": 0.728378,
      "oracle_gain_bacc": -0.006757,
      "oracle_gain_acc": -0.006757,
      "beneficial": false,
      "harmful": true,
      "near_zero": false,
      "gain_abs": 0.006757,
      "gain_bin": "harm",
      "oracle_only": true
    },
    {
      "dataset": "BNCI2014_004",
      "target_subject": 4,
      "seed": 1,
      "n_trials": 740,
      "identity_bacc": 0.764865,
      "adapt_bacc": 0.768919,
      "oracle_gain_bacc": 0.004054,
      "oracle_gain_acc": 0.004054,
      "beneficial": false,
      "harmful": false,
      "near_zero": true,
      "gain_abs": 0.004054,
      "gain_bin": "near_zero",
      "oracle_only": true
    },
    {
      "dataset": "BNCI2014_004",
      "target_subject": 4,
      "seed": 2,
      "n_trials": 740,
      "identity_bacc": 0.774324,
      "adapt_bacc": 0.786486,
      "oracle_gain_bacc": 0.012162,
      "oracle_gain_acc": 0.012162,
      "beneficial": true,
      "harmful": false,
      "near_zero": false,
      "gain_abs": 0.012162,
      "gain_bin": "benefit",
      "oracle_only": true
    },
    {
      "dataset": "BNCI2014_004",
      "target_subject": 5,
      "seed": 0,
      "n_trials": 740,
      "identity_bacc": 0.571622,
      "adapt_bacc": 0.547297,
      "oracle_gain_bacc": -0.024324,
      "oracle_gain_acc": -0.024324,
      "beneficial": false,
      "harmful": true,
      "near_zero": false,
      "gain_abs": 0.024324,
      "gain_bin": "harm",
      "oracle_only": true
    },
    {
      "dataset": "BNCI2014_004",
      "target_subject": 5,
      "seed": 1,
      "n_trials": 740,
      "identity_bacc": 0.608108,
      "adapt_bacc": 0.558108,
      "oracle_gain_bacc": -0.05,
      "oracle_gain_acc": -0.05,
      "beneficial": false,
      "harmful": true,
      "near_zero": false,
      "gain_abs": 0.05,
      "gain_bin": "harm",
      "oracle_only": true
    },
    {
      "dataset": "BNCI2014_004",
      "target_subject": 5,
      "seed": 2,
      "n_trials": 740,
      "identity_bacc": 0.562162,
      "adapt_bacc": 0.504054,
      "oracle_gain_bacc": -0.058108,
      "oracle_gain_acc": -0.058108,
      "beneficial": false,
      "harmful": true,
      "near_zero": false,
      "gain_abs": 0.058108,
      "gain_bin": "harm",
      "oracle_only": true
    },
    {
      "dataset": "BNCI2014_004",
      "target_subject": 6,
      "seed": 0,
      "n_trials": 720,
      "identity_bacc": 0.613889,
      "adapt_bacc": 0.609722,
      "oracle_gain_bacc": -0.004167,
      "oracle_gain_acc": -0.004167,
      "beneficial": false,
      "harmful": false,
      "near_zero": true,
      "gain_abs": 0.004167,
      "gain_bin": "near_zero",
      "oracle_only": true
    },
    {
      "dataset": "BNCI2014_004",
      "target_subject": 6,
      "seed": 1,
      "n_trials": 720,
      "identity_bacc": 0.663889,
      "adapt_bacc": 0.594444,
      "oracle_gain_bacc": -0.069444,
      "oracle_gain_acc": -0.069444,
      "beneficial": false,
      "harmful": true,
      "near_zero": false,
      "gain_abs": 0.069444,
      "gain_bin": "harm",
      "oracle_only": true
    },
    {
      "dataset": "BNCI2014_004",
      "target_subject": 6,
      "seed": 2,
      "n_trials": 720,
      "identity_bacc": 0.627778,
      "adapt_bacc": 0.573611,
      "oracle_gain_bacc": -0.054167,
      "oracle_gain_acc": -0.054167,
      "beneficial": false,
      "harmful": true,
      "near_zero": false,
      "gain_abs": 0.054167,
      "gain_bin": "harm",
      "oracle_only": true
    },
    {
      "dataset": "BNCI2014_004",
      "target_subject": 7,
      "seed": 0,
      "n_trials": 720,
      "identity_bacc": 0.552778,
      "adapt_bacc": 0.530556,
      "oracle_gain_bacc": -0.022222,
      "oracle_gain_acc": -0.022222,
      "beneficial": false,
      "harmful": true,
      "near_zero": false,
      "gain_abs": 0.022222,
      "gain_bin": "harm",
      "oracle_only": true
    },
    {
      "dataset": "BNCI2014_004",
      "target_subject": 7,
      "seed": 1,
      "n_trials": 720,
      "identity_bacc": 0.618056,
      "adapt_bacc": 0.577778,
      "oracle_gain_bacc": -0.040278,
      "oracle_gain_acc": -0.040278,
      "beneficial": false,
      "harmful": true,
      "near_zero": false,
      "gain_abs": 0.040278,
      "gain_bin": "harm",
      "oracle_only": true
    },
    {
      "dataset": "BNCI2014_004",
      "target_subject": 7,
      "seed": 2,
      "n_trials": 720,
      "identity_bacc": 0.608333,
      "adapt_bacc": 0.5875,
      "oracle_gain_bacc": -0.020833,
      "oracle_gain_acc": -0.020833,
      "beneficial": false,
      "harmful": true,
      "near_zero": false,
      "gain_abs": 0.020833,
      "gain_bin": "harm",
      "oracle_only": true
    },
    {
      "dataset": "BNCI2014_004",
      "target_subject": 8,
      "seed": 0,
      "n_trials": 760,
      "identity_bacc": 0.694737,
      "adapt_bacc": 0.665789,
      "oracle_gain_bacc": -0.028947,
      "oracle_gain_acc": -0.028947,
      "beneficial": false,
      "harmful": true,
      "near_zero": false,
      "gain_abs": 0.028947,
      "gain_bin": "harm",
      "oracle_only": true
    },
    {
      "dataset": "BNCI2014_004",
      "target_subject": 8,
      "seed": 1,
      "n_trials": 760,
      "identity_bacc": 0.727632,
      "adapt_bacc": 0.630263,
      "oracle_gain_bacc": -0.097368,
      "oracle_gain_acc": -0.097368,
      "beneficial": false,
      "harmful": true,
      "near_zero": false,
      "gain_abs": 0.097368,
      "gain_bin": "harm",
      "oracle_only": true
    },
    {
      "dataset": "BNCI2014_004",
      "target_subject": 8,
      "seed": 2,
      "n_trials": 760,
      "identity_bacc": 0.682895,
      "adapt_bacc": 0.625,
      "oracle_gain_bacc": -0.057895,
      "oracle_gain_acc": -0.057895,
      "beneficial": false,
      "harmful": true,
      "near_zero": false,
      "gain_abs": 0.057895,
      "gain_bin": "harm",
      "oracle_only": true
    },
    {
      "dataset": "BNCI2014_004",
      "target_subject": 9,
      "seed": 0,
      "n_trials": 720,
      "identity_bacc": 0.631944,
      "adapt_bacc": 0.604167,
      "oracle_gain_bacc": -0.027778,
      "oracle_gain_acc": -0.027778,
      "beneficial": false,
      "harmful": true,
      "near_zero": false,
      "gain_abs": 0.027778,
      "gain_bin": "harm",
      "oracle_only": true
    },
    {
      "dataset": "BNCI2014_004",
      "target_subject": 9,
      "seed": 1,
      "n_trials": 720,
      "identity_bacc": 0.623611,
      "adapt_bacc": 0.586111,
      "oracle_gain_bacc": -0.0375,
      "oracle_gain_acc": -0.0375,
      "beneficial": false,
      "harmful": true,
      "near_zero": false,
      "gain_abs": 0.0375,
      "gain_bin": "harm",
      "oracle_only": true
    },
    {
      "dataset": "BNCI2014_004",
      "target_subject": 9,
      "seed": 2,
      "n_trials": 720,
      "identity_bacc": 0.625,
      "adapt_bacc": 0.6,
      "oracle_gain_bacc": -0.025,
      "oracle_gain_acc": -0.025,
      "beneficial": false,
      "harmful": true,
      "near_zero": false,
      "gain_abs": 0.025,
      "gain_bin": "harm",
      "oracle_only": true
    }
  ],
  "claim_boundary": "oracle-only benefit anatomy; NOT deployment-observable under R0/R1; used only to characterise the problem, never as a predictor or deployable signal."
}
