{
  "condition": "PD",
  "domain": "cohort",
  "dec_domain": "cohort",
  "cohorts": [
    "ds002778",
    "ds003490",
    "ds004584"
  ],
  "config": {
    "condition": "PD",
    "cohorts": null,
    "backbone": "EEGNet",
    "domain": "cohort",
    "dec_domain": "",
    "configs": [
      "erm:0",
      "lpc_prior:0.1"
    ],
    "epochs": 120,
    "bs": 64,
    "warmup": 30,
    "n_inner": 2,
    "device": "auto",
    "sampler": "classbal",
    "prior": "empirical",
    "beta": 0.0,
    "seed": 0,
    "balance": false,
    "label_correct": false,
    "reweight_dual": false,
    "transduct": "all",
    "transduct_shrink": 0.1,
    "transduct_gate": 0.0,
    "dec_margin": null,
    "decoder_null_perms": 0,
    "decoder_null_quantile": 0.95,
    "out": "results/r3_dualpc2/r3_PD_s0.json"
  },
  "summary": {
    "erm:0": {
      "per_target_balanced_acc_mean": 0.5921633887365871,
      "worst_target_balanced_acc": 0.5208333333333334,
      "leakage_kl": 0.21731561919053397,
      "leakage_kl_rw": 0.21670867999394736,
      "marginal_leakage_kl": 0.2173715978860855,
      "marginal_leakage_kl_rw": 0.2121973087390264,
      "marginal_leakage_advantage": 0.14823702445666462,
      "marginal_leakage_advantage_rw": 0.14500362798071095,
      "leakage_advantage_rw": 0.14247012443445087,
      "decoder_cmi": 0.0005369658271471659,
      "decoder_cmi_rw": 0.0013581812381744385,
      "decoder_cmi_res": 0.0009241849184036255,
      "decoder_cmi_res_rw": 0.000561798612276713,
      "decoder_js_res": 0.0001880044631737595,
      "decoder_js_res_rw": 0.0001640060751621301,
      "decoder_valid_frac": 1.0,
      "decoder_min_domain_classes": 2,
      "decoder_single_class_frac": 0.0,
      "inloop_reg": 0.0,
      "inloop_dec": 0.0,
      "inloop_dec_loss": 0.0,
      "train_dec_margin": 0.02,
      "per_cohort": {
        "ds002778": 52.1,
        "ds003490": 64.6,
        "ds004584": 60.9
      },
      "transduct_balanced_acc_mean": 0.626432874638161,
      "probe_balanced_acc_mean": 0.5936056500521129,
      "ts_probe_balanced_acc_mean": 0.5936056500521129,
      "ts_coral_balanced_acc_mean": 0.626432874638161,
      "ts_prior_balanced_acc_mean": 0.5835352629448128,
      "ts_coral_prior_balanced_acc_mean": 0.62819556200592,
      "ts_balanced_acc_mean": 0.626432874638161,
      "decoder_valid_n": 3,
      "decoder_cmi_valid_mean": 0.0005369658271471659,
      "decoder_cmi_rw_valid_mean": 0.0013581812381744385,
      "decoder_cmi_res_valid_mean": 0.0009241849184036255,
      "decoder_cmi_res_rw_valid_mean": 0.000561798612276713,
      "decoder_js_res_valid_mean": 0.0001880044631737595,
      "decoder_js_res_rw_valid_mean": 0.0001640060751621301,
      "decoder_cmi_res_null_q_valid_mean": null,
      "decoder_cmi_res_excess_valid_mean": null,
      "decoder_cmi_res_rw_null_q_valid_mean": null,
      "decoder_cmi_res_rw_excess_valid_mean": null,
      "decoder_js_res_null_q_valid_mean": null,
      "decoder_js_res_excess_valid_mean": null,
      "decoder_js_res_rw_null_q_valid_mean": null,
      "decoder_js_res_rw_excess_valid_mean": null
    },
    "lpc_prior:0.1": {
      "per_target_balanced_acc_mean": 0.5969654653708049,
      "worst_target_balanced_acc": 0.5163541666666667,
      "leakage_kl": 0.03176074350873629,
      "leakage_kl_rw": 0.03137608431279659,
      "marginal_leakage_kl": 0.03877963498234749,
      "marginal_leakage_kl_rw": 0.028894248108069103,
      "marginal_leakage_advantage": 0.01695639617921167,
      "marginal_leakage_advantage_rw": 0.016613460651090966,
      "leakage_advantage_rw": 0.018938359496881385,
      "decoder_cmi": 0.00019043187300364176,
      "decoder_cmi_rw": 0.001362594465414683,
      "decoder_cmi_res": 0.0003396222988764445,
      "decoder_cmi_res_rw": 8.355081081390381e-05,
      "decoder_js_res": 7.482004245199884e-05,
      "decoder_js_res_rw": 3.906571267483135e-05,
      "decoder_valid_frac": 1.0,
      "decoder_min_domain_classes": 2,
      "decoder_single_class_frac": 0.0,
      "inloop_reg": 0.09956603468417558,
      "inloop_dec": 0.0,
      "inloop_dec_loss": 0.0,
      "train_dec_margin": 0.02,
      "per_cohort": {
        "ds002778": 51.6,
        "ds003490": 65.0,
        "ds004584": 62.5
      },
      "transduct_balanced_acc_mean": 0.6165726436963299,
      "probe_balanced_acc_mean": 0.5925780497758811,
      "ts_probe_balanced_acc_mean": 0.5925780497758811,
      "ts_coral_balanced_acc_mean": 0.6165726436963299,
      "ts_prior_balanced_acc_mean": 0.5817399608265518,
      "ts_coral_prior_balanced_acc_mean": 0.6166081407143573,
      "ts_balanced_acc_mean": 0.6165726436963299,
      "decoder_valid_n": 3,
      "decoder_cmi_valid_mean": 0.00019043187300364176,
      "decoder_cmi_rw_valid_mean": 0.001362594465414683,
      "decoder_cmi_res_valid_mean": 0.0003396222988764445,
      "decoder_cmi_res_rw_valid_mean": 8.355081081390381e-05,
      "decoder_js_res_valid_mean": 7.482004245199884e-05,
      "decoder_js_res_rw_valid_mean": 3.906571267483135e-05,
      "decoder_cmi_res_null_q_valid_mean": null,
      "decoder_cmi_res_excess_valid_mean": null,
      "decoder_cmi_res_rw_null_q_valid_mean": null,
      "decoder_cmi_res_rw_excess_valid_mean": null,
      "decoder_js_res_null_q_valid_mean": null,
      "decoder_js_res_excess_valid_mean": null,
      "decoder_js_res_rw_null_q_valid_mean": null,
      "decoder_js_res_rw_excess_valid_mean": null
    }
  },
  "folds": {
    "erm:0": [
      {
        "held_out": "ds002778",
        "balanced_acc": 0.5208333333333334,
        "macro_f1": 0.4030808729139923,
        "leakage_kl": 0.15740720927715302,
        "leakage_kl_rw": 0.1545783430337906,
        "leakage_advantage_rw": 0.10663615560640738,
        "marginal_leakage_kl": 0.15119551122188568,
        "marginal_leakage_kl_rw": 0.14670871198177338,
        "marginal_leakage_advantage": 0.1125858123569794,
        "marginal_leakage_advantage_rw": 0.10800915331807781,
        "decoder_cmi": 0.0009185671806335449,
        "decoder_cmi_rw": 0.002235814929008484,
        "decoder_cmi_res": 0.0015529990196228027,
        "decoder_cmi_res_rw": 0.0009404122829437256,
        "decoder_js_res": 0.00022262574930209666,
        "decoder_js_res_rw": 0.00023090228205546737,
        "decoder_valid": true,
        "decoder_n_domains": 2,
        "decoder_min_domain_classes": 2,
        "decoder_mean_domain_classes": 2.0,
        "decoder_single_class_frac": 0.0,
        "decoder_domain_class_spans": [
          2,
          2
        ],
        "decoder_domain_counts": [
          2000,
          5283
        ],
        "inloop_reg": 0.0,
        "inloop_dec": 0.0,
        "inloop_dec_loss": 0.0,
        "train_dec_margin": 0.02,
        "train_sampler": "classbal",
        "n_test": 1240,
        "ts_probe_balanced_acc": 0.5313541666666667,
        "ts_coral_balanced_acc": 0.64390625,
        "ts_prior_balanced_acc": 0.5042187499999999,
        "ts_coral_prior_balanced_acc": 0.6454166666666666,
        "ts_balanced_acc": 0.64390625,
        "probe_balanced_acc": 0.5313541666666667
      },
      {
        "held_out": "ds003490",
        "balanced_acc": 0.6465,
        "macro_f1": 0.6445799319373083,
        "leakage_kl": 0.21607089042663574,
        "leakage_kl_rw": 0.21501459181308746,
        "leakage_advantage_rw": 0.10884006131834445,
        "marginal_leakage_kl": 0.22191891074180603,
        "marginal_leakage_kl_rw": 0.2099393606185913,
        "marginal_leakage_advantage": 0.10373019928461935,
        "marginal_leakage_advantage_rw": 0.10066428206438427,
        "decoder_cmi": 0.0006923303008079529,
        "decoder_cmi_rw": 0.0018387287855148315,
        "decoder_cmi_res": 0.0006950274109840393,
        "decoder_cmi_res_rw": 1.3694167137145996e-05,
        "decoder_js_res": 0.0002083115978166461,
        "decoder_js_res_rw": 0.0001350041275145486,
        "decoder_valid": true,
        "decoder_n_domains": 2,
        "decoder_min_domain_classes": 2,
        "decoder_mean_domain_classes": 2.0,
        "decoder_single_class_frac": 0.0,
        "decoder_domain_class_spans": [
          2,
          2
        ],
        "decoder_domain_counts": [
          1240,
          5283
        ],
        "inloop_reg": 0.0,
        "inloop_dec": 0.0,
        "inloop_dec_loss": 0.0,
        "train_dec_margin": 0.02,
        "train_sampler": "classbal",
        "n_test": 2000,
        "ts_probe_balanced_acc": 0.639,
        "ts_coral_balanced_acc": 0.6285000000000001,
        "ts_prior_balanced_acc": 0.639,
        "ts_coral_prior_balanced_acc": 0.629,
        "ts_balanced_acc": 0.6285000000000001,
        "probe_balanced_acc": 0.639
      },
      {
        "held_out": "ds004584",
        "balanced_acc": 0.6091568328764281,
        "macro_f1": 0.5646560161901828,
        "leakage_kl": 0.2784687578678131,
        "leakage_kl_rw": 0.280533105134964,
        "leakage_advantage_rw": 0.2119341563786008,
        "marginal_leakage_kl": 0.2790003716945648,
        "marginal_leakage_kl_rw": 0.2799438536167145,
        "marginal_leakage_advantage": 0.22839506172839508,
        "marginal_leakage_advantage_rw": 0.22633744855967075,
        "decoder_cmi": 0.0,
        "decoder_cmi_rw": 0.0,
        "decoder_cmi_res": 0.0005245283246040344,
        "decoder_cmi_res_rw": 0.0007312893867492676,
        "decoder_js_res": 0.00013307604240253568,
        "decoder_js_res_rw": 0.00012611181591637433,
        "decoder_valid": true,
        "decoder_n_domains": 2,
        "decoder_min_domain_classes": 2,
        "decoder_mean_domain_classes": 2.0,
        "decoder_single_class_frac": 0.0,
        "decoder_domain_class_spans": [
          2,
          2
        ],
        "decoder_domain_counts": [
          1240,
          2000
        ],
        "inloop_reg": 0.0,
        "inloop_dec": 0.0,
        "inloop_dec_loss": 0.0,
        "train_dec_margin": 0.02,
        "train_sampler": "classbal",
        "n_test": 5283,
        "ts_probe_balanced_acc": 0.6104627834896716,
        "ts_coral_balanced_acc": 0.6068923739144831,
        "ts_prior_balanced_acc": 0.6073870388344385,
        "ts_coral_prior_balanced_acc": 0.6101700193510932,
        "ts_balanced_acc": 0.6068923739144831,
        "probe_balanced_acc": 0.6104627834896716
      }
    ],
    "lpc_prior:0.1": [
      {
        "held_out": "ds002778",
        "balanced_acc": 0.5163541666666667,
        "macro_f1": 0.4340448412549549,
        "leakage_kl": 0.03546525165438652,
        "leakage_kl_rw": 0.03439983353018761,
        "leakage_advantage_rw": 0.0022883295194507935,
        "marginal_leakage_kl": 0.04869942367076874,
        "marginal_leakage_kl_rw": 0.03206787258386612,
        "marginal_leakage_advantage": 0.0004576659038901809,
        "marginal_leakage_advantage_rw": 0.0004576659038901809,
        "decoder_cmi": 0.0005712956190109253,
        "decoder_cmi_rw": 0.0039925724267959595,
        "decoder_cmi_res": 0.0010188668966293335,
        "decoder_cmi_res_rw": 0.0002506524324417114,
        "decoder_js_res": 0.00010388534428784624,
        "decoder_js_res_rw": 3.322100383229554e-05,
        "decoder_valid": true,
        "decoder_n_domains": 2,
        "decoder_min_domain_classes": 2,
        "decoder_mean_domain_classes": 2.0,
        "decoder_single_class_frac": 0.0,
        "decoder_domain_class_spans": [
          2,
          2
        ],
        "decoder_domain_counts": [
          2000,
          5283
        ],
        "inloop_reg": 0.09247659905030664,
        "inloop_dec": 0.0,
        "inloop_dec_loss": 0.0,
        "train_dec_margin": 0.02,
        "train_sampler": "classbal",
        "n_test": 1240,
        "ts_probe_balanced_acc": 0.5271875,
        "ts_coral_balanced_acc": 0.6051562500000001,
        "ts_prior_balanced_acc": 0.5031249999999999,
        "ts_coral_prior_balanced_acc": 0.6051562500000001,
        "ts_balanced_acc": 0.6051562500000001,
        "probe_balanced_acc": 0.5271875
      },
      {
        "held_out": "ds003490",
        "balanced_acc": 0.6495,
        "macro_f1": 0.6468577010335583,
        "leakage_kl": 0.019922859966754913,
        "leakage_kl_rw": 0.019956013187766075,
        "leakage_advantage_rw": 0.0,
        "marginal_leakage_kl": 0.02985456958413124,
        "marginal_leakage_kl_rw": 0.01698685809969902,
        "marginal_leakage_advantage": 0.0,
        "marginal_leakage_advantage_rw": 0.0,
        "decoder_cmi": 0.0,
        "decoder_cmi_rw": 9.52109694480896e-05,
        "decoder_cmi_res": 0.0,
        "decoder_cmi_res_rw": 0.0,
        "decoder_js_res": 7.782836473779753e-05,
        "decoder_js_res_rw": 3.79234625142999e-05,
        "decoder_valid": true,
        "decoder_n_domains": 2,
        "decoder_min_domain_classes": 2,
        "decoder_mean_domain_classes": 2.0,
        "decoder_single_class_frac": 0.0,
        "decoder_domain_class_spans": [
          2,
          2
        ],
        "decoder_domain_counts": [
          1240,
          5283
        ],
        "inloop_reg": 0.10461108674212258,
        "inloop_dec": 0.0,
        "inloop_dec_loss": 0.0,
        "train_dec_margin": 0.02,
        "train_sampler": "classbal",
        "n_test": 2000,
        "ts_probe_balanced_acc": 0.628,
        "ts_coral_balanced_acc": 0.6335,
        "ts_prior_balanced_acc": 0.623,
        "ts_coral_prior_balanced_acc": 0.636,
        "ts_balanced_acc": 0.6335,
        "probe_balanced_acc": 0.628
      },
      {
        "held_out": "ds004584",
        "balanced_acc": 0.6250422294457479,
        "macro_f1": 0.5740674828275216,
        "leakage_kl": 0.039894118905067444,
        "leakage_kl_rw": 0.039772406220436096,
        "leakage_advantage_rw": 0.05452674897119336,
        "marginal_leakage_kl": 0.03778491169214249,
        "marginal_leakage_kl_rw": 0.037628013640642166,
        "marginal_leakage_advantage": 0.05041152263374482,
        "marginal_leakage_advantage_rw": 0.04938271604938271,
        "decoder_cmi": 0.0,
        "decoder_cmi_rw": 0.0,
        "decoder_cmi_res": 0.0,
        "decoder_cmi_res_rw": 0.0,
        "decoder_js_res": 4.2746418330352753e-05,
        "decoder_js_res_rw": 4.6052671677898616e-05,
        "decoder_valid": true,
        "decoder_n_domains": 2,
        "decoder_min_domain_classes": 2,
        "decoder_mean_domain_classes": 2.0,
        "decoder_single_class_frac": 0.0,
        "decoder_domain_class_spans": [
          2,
          2
        ],
        "decoder_domain_counts": [
          1240,
          2000
        ],
        "inloop_reg": 0.10161041826009751,
        "inloop_dec": 0.0,
        "inloop_dec_loss": 0.0,
        "train_dec_margin": 0.02,
        "train_sampler": "classbal",
        "n_test": 5283,
        "ts_probe_balanced_acc": 0.6225466493276431,
        "ts_coral_balanced_acc": 0.6110616810889897,
        "ts_prior_balanced_acc": 0.6190948824796554,
        "ts_coral_prior_balanced_acc": 0.6086681721430719,
        "ts_balanced_acc": 0.6110616810889897,
        "probe_balanced_acc": 0.6225466493276431
      }
    ]
  }
}