{
  "dataset": "BNCI2015_001",
  "subject": "3",
  "seed": 0,
  "status": "ok",
  "C": 2,
  "n_cal": 200,
  "n_query": 200,
  "cal_session": [
    "0A"
  ],
  "query_sessions": [
    "1B"
  ],
  "n_draws": 50,
  "n_tau_draws": 10,
  "init_param_diff": 5.743313463536715e-05,
  "endpoints": {
    "1": {
      "U_H0": 0.555,
      "U_H1": 0.6397999999999999,
      "U_H1W": 0.6397999999999999,
      "U_H2": 0.5948,
      "U_H3": 0.6755,
      "U_H4": 0.555,
      "dU_center": -0.04499999999999993,
      "dU_MAP_frozen": 0.03979999999999995,
      "dU_gate_frozen": 0.0,
      "dU_gate_map": -0.03979999999999995,
      "dU_init_bacc": 0.0,
      "U_H2_minus_H3": -0.0807,
      "tau0": 1.0,
      "taus": 10.0,
      "gate": 0
    },
    "2": {
      "U_H0": 0.555,
      "U_H1": 0.6980000000000001,
      "U_H1W": 0.6980000000000001,
      "U_H2": 0.6631,
      "U_H3": 0.7243999999999998,
      "U_H4": 0.6631,
      "dU_center": -0.03490000000000004,
      "dU_MAP_frozen": 0.10809999999999997,
      "dU_gate_frozen": 0.10809999999999997,
      "dU_gate_map": 0.0,
      "dU_init_bacc": 0.0,
      "U_H2_minus_H3": -0.0612999999999998,
      "tau0": 1.0,
      "taus": 10.0,
      "gate": 1
    },
    "4": {
      "U_H0": 0.555,
      "U_H1": 0.7128,
      "U_H1W": 0.7128,
      "U_H2": 0.7458,
      "U_H3": 0.7373000000000002,
      "U_H4": 0.7458,
      "dU_center": 0.03300000000000003,
      "dU_MAP_frozen": 0.19079999999999997,
      "dU_gate_frozen": 0.19079999999999997,
      "dU_gate_map": 0.0,
      "dU_init_bacc": 0.0,
      "U_H2_minus_H3": 0.008499999999999841,
      "tau0": 1.0,
      "taus": 10.0,
      "gate": 1
    },
    "8": {
      "U_H0": 0.555,
      "U_H1": 0.7699000000000001,
      "U_H1W": 0.7699000000000001,
      "U_H2": 0.8245000000000001,
      "U_H3": 0.7241999999999998,
      "U_H4": 0.8245000000000001,
      "dU_center": 0.05459999999999998,
      "dU_MAP_frozen": 0.2695000000000001,
      "dU_gate_frozen": 0.2695000000000001,
      "dU_gate_map": 0.0,
      "dU_init_bacc": 0.0,
      "U_H2_minus_H3": 0.10030000000000028,
      "tau0": 1.0,
      "taus": 10.0,
      "gate": 1
    },
    "16": {
      "U_H0": 0.555,
      "U_H1": 0.7883999999999999,
      "U_H1W": 0.7883999999999999,
      "U_H2": 0.8465,
      "U_H3": 0.7223999999999999,
      "U_H4": 0.8465,
      "dU_center": 0.05810000000000015,
      "dU_MAP_frozen": 0.2915,
      "dU_gate_frozen": 0.2915,
      "dU_gate_map": 0.0,
      "dU_init_bacc": 0.0,
      "U_H2_minus_H3": 0.1241000000000001,
      "tau0": 1.0,
      "taus": 10.0,
      "gate": 1
    },
    "32": {
      "U_H0": 0.555,
      "U_H1": 0.7998999999999999,
      "U_H1W": 0.7998999999999999,
      "U_H2": 0.8249999999999998,
      "U_H3": 0.7119000000000001,
      "U_H4": 0.8249999999999998,
      "dU_center": 0.0250999999999999,
      "dU_MAP_frozen": 0.2699999999999998,
      "dU_gate_frozen": 0.2699999999999998,
      "dU_gate_map": 0.0,
      "dU_init_bacc": 0.0,
      "U_H2_minus_H3": 0.11309999999999976,
      "tau0": 1.0,
      "taus": 10.0,
      "gate": 1
    },
    "Full": {
      "U_H0": 0.555,
      "U_H1": 0.8200000000000001,
      "U_H1W": 0.8200000000000001,
      "U_H2": 0.79,
      "U_H3": 0.7,
      "U_H4": 0.79,
      "dU_center": -0.030000000000000027,
      "dU_MAP_frozen": 0.235,
      "dU_gate_frozen": 0.235,
      "dU_gate_map": 0.0,
      "dU_init_bacc": 0.0,
      "U_H2_minus_H3": 0.09000000000000008,
      "tau0": 1.0,
      "taus": 10.0,
      "gate": 1
    }
  },
  "specificity": {
    "status": "ok",
    "rank": 8,
    "n_matched": 50,
    "n_tried": 365,
    "informed_srcval": 0.6609999999999999,
    "dGh_specific": {
      "ridge_k1": {
        "informed": 0.07280000000000002,
        "random_mean": -0.013427999999999995,
        "specific": 0.08622800000000001
      },
      "map_k1": {
        "informed": 0.04210000000000003,
        "random_mean": 0.03768,
        "specific": 0.004420000000000035
      },
      "ridge_k8": {
        "informed": 0.11190000000000003,
        "random_mean": 0.09031800000000002,
        "specific": 0.021582000000000004
      },
      "map_k8": {
        "informed": 0.09860000000000003,
        "random_mean": 0.10954000000000001,
        "specific": -0.010939999999999978
      },
      "ridge_kFull": {
        "informed": 0.16000000000000003,
        "random_mean": 0.1866,
        "specific": -0.026599999999999957
      },
      "map_kFull": {
        "informed": 0.15500000000000003,
        "random_mean": 0.1782,
        "specific": -0.02319999999999997
      }
    }
  },
  "headroom": {
    "frozen_query_bacc": 0.555,
    "frozen_query_nll": 1.5712510409244296,
    "fullcal_query_bacc": 0.8200000000000001,
    "fullcal_gain": 0.265,
    "angle_Ws_Wt_deg": 24.869686576585018,
    "bias_displacement": 3.988068551189355,
    "direction_displacement": 1.0972581664110428,
    "cal_cov_condition": 26.513195433676085,
    "class_prior_shift": 0.0,
    "cal_query_mean_drift": 1.4452642805787914
  },
  "tau0": {
    "1": 1.0,
    "2": 1.0,
    "4": 1.0,
    "8": 1.0,
    "16": 1.0,
    "32": 1.0,
    "Full": 1.0
  },
  "taus": {
    "1": 10.0,
    "2": 10.0,
    "4": 10.0,
    "8": 10.0,
    "16": 10.0,
    "32": 10.0,
    "Full": 10.0
  },
  "gate": {
    "1": 0,
    "2": 1,
    "4": 1,
    "8": 1,
    "16": 1,
    "32": 1,
    "Full": 1
  },
  "firewall": {
    "source_only_construction": true,
    "tau_source_only": true,
    "gate_source_only": true,
    "Ycal_used_for_head_adapt": true,
    "Yquery_used_for_selection": false,
    "Yquery_used_for_outcome": true
  }
}